xbasic/Interpreter.py
xbasic/__init__.py
xbasic/builtinfunction.py
xbasic/function.py
xbasic/init_interp.py
xbasic/lexer.py
xbasic/list.py
xbasic/main.py
xbasic/number.py
xbasic/parser.py
xbasic/string_value.py
xbasic/value.py
xbasic/context_handler/__init__.py
xbasic/context_handler/context.py
xbasic/context_handler/symbol_table.py
xbasic/error_handler/__init__.py
xbasic/error_handler/error.py
xbasic/error_handler/rterror.py
xbasic/error_handler/rtresult.py
xbasic/error_handler/string_with_arrows.py
xbasic/utils/__init__.py
xbasic/utils/nodes.py
xbasic/utils/parse_result.py
xbasic/utils/position.py
xbasic/utils/token.py
xbasic/utils/token_list.py
xbasic-1.2.2.dist-info/LICENSE
xbasic-1.2.2.dist-info/METADATA
xbasic-1.2.2.dist-info/WHEEL
xbasic-1.2.2.dist-info/entry_points.txt
xbasic-1.2.2.dist-info/top_level.txt
xbasic-1.2.2.dist-info/RECORD
